{"version": "1", "message": "ERROR: Hidden Testcases server unreachable.", "problem_id": "ads1_m14_a2", "user_id": "BhavaniChoudary", "score": {"sample": {"0": {"execution_time": 0.37432098388671875, "passed": true}, "1": {"execution_time": 0.38936376571655273, "passed": true}, "2": {"execution_time": 0.38825488090515137, "passed": true}, "3": {"execution_time": 0.37276506423950195, "passed": true}, "4": {"execution_time": 0.39385080337524414, "passed": true}, "5": {"execution_time": 0.37779951095581055, "passed": true}}}, "check_style_score": "0/1"}